distro_support/__init__.py
distro_support/_debian_like_downloader.py
distro_support/_distro.py
distro_support/debian.json
distro_support/debian.py
distro_support/errors.py
distro_support/py.typed
distro_support/ubuntu.json
distro_support/ubuntu.py
distro_support-2025.12.16.dist-info/METADATA
distro_support-2025.12.16.dist-info/WHEEL
distro_support-2025.12.16.dist-info/RECORD
