Metadata-Version: 2.4
Name: distro-support
Version: 2025.12.16
Summary: Get information about support dates for Linux distributions
Author-email: Alex Lowe <alex@lowe.dev>
Requires-Python: >=3.8
Requires-Dist: typing-extensions>=4.13.2
